LICENSE
MANIFEST.in
NOTICE
Pipfile
README.md
setup.py
gdcdictionary/__init__.py
gdcdictionary/schema_test.py
gdcdictionary.egg-info/PKG-INFO
gdcdictionary.egg-info/SOURCES.txt
gdcdictionary.egg-info/dependency_links.txt
gdcdictionary.egg-info/requires.txt
gdcdictionary.egg-info/top_level.txt
gdcdictionary/schemas/_definitions.yaml
gdcdictionary/schemas/_settings.yaml
gdcdictionary/schemas/_terms.yaml
gdcdictionary/schemas/acknowledgement.yaml
gdcdictionary/schemas/aligned_reads_index.yaml
gdcdictionary/schemas/aliquot.yaml
gdcdictionary/schemas/case.yaml
gdcdictionary/schemas/clinical_test.yaml
gdcdictionary/schemas/core_metadata_collection.yaml
gdcdictionary/schemas/demographic.yaml
gdcdictionary/schemas/diagnosis.yaml
gdcdictionary/schemas/experiment.yaml
gdcdictionary/schemas/experimental_metadata.yaml
gdcdictionary/schemas/exposure.yaml
gdcdictionary/schemas/family_history.yaml
gdcdictionary/schemas/keyword.yaml
gdcdictionary/schemas/program.yaml
gdcdictionary/schemas/project.yaml
gdcdictionary/schemas/publication.yaml
gdcdictionary/schemas/read_group.yaml
gdcdictionary/schemas/read_group_qc.yaml
gdcdictionary/schemas/sample.yaml
gdcdictionary/schemas/slide.yaml
gdcdictionary/schemas/slide_count.yaml
gdcdictionary/schemas/slide_image.yaml
gdcdictionary/schemas/submitted_aligned_reads.yaml
gdcdictionary/schemas/submitted_copy_number.yaml
gdcdictionary/schemas/submitted_methylation.yaml
gdcdictionary/schemas/submitted_somatic_mutation.yaml
gdcdictionary/schemas/submitted_unaligned_reads.yaml
gdcdictionary/schemas/treatment.yaml
gdcdictionary/schemas/projects/project1.yaml