Metadata-Version: 1.0
Name: gdcdictionary
Version: 1.2.0
Summary: Gen3 generic data dictionary
Home-page: UNKNOWN
Author: UNKNOWN
Author-email: UNKNOWN
License: Apache
Platform: UNKNOWN
